sense_text_extractor/__init__.py
sense_text_extractor/text_extract_pb2.py
sense_text_extractor/text_extract_pb2_grpc.py
sense_text_extractor/text_extractor.py
sense_text_extractor-0.0.5.dist-info/METADATA
sense_text_extractor-0.0.5.dist-info/WHEEL
sense_text_extractor-0.0.5.dist-info/top_level.txt
sense_text_extractor-0.0.5.dist-info/RECORD
